tracker2k/__init__.py
tracker2k/wrappers/__init__.py
tracker2k/wrappers/openai.py
tracker2k-0.0.3.dist-info/METADATA
tracker2k-0.0.3.dist-info/WHEEL
tracker2k-0.0.3.dist-info/top_level.txt
tracker2k-0.0.3.dist-info/RECORD
