Metadata-Version: 2.1
Name: tracker2k
Version: 0.0.3
Summary: A log tracking client integration code for OpenAI agents sdk
Home-page: https://github.com/bxplucky/tracker2k
Author: bxplucky
Author-email: bxplucky@gmail.com
Classifier: Programming Language :: Python :: 3
Classifier: License :: OSI Approved :: MIT License
Classifier: Operating System :: OS Independent
Requires-Python: >=3.6
Provides-Extra: dev
Requires-Dist: pytest>=6.0; extra == "dev"
